README.rst
_description.org
lh-agpl3-LICENSE.txt
pyproject.toml
setup.py
bin/gcipher
bisos/__init__.py
bisos.gcipher.egg-info/PKG-INFO
bisos.gcipher.egg-info/SOURCES.txt
bisos.gcipher.egg-info/dependency_links.txt
bisos.gcipher.egg-info/not-zip-safe
bisos.gcipher.egg-info/requires.txt
bisos.gcipher.egg-info/top_level.txt
bisos/gcipher/AutomaticClass.py
bisos/gcipher/Const.py
bisos/gcipher/GtkAttributesFacade.py
bisos/gcipher/LibGladeApplication.py
bisos/gcipher/MainCLI.py
bisos/gcipher/MainGUI.py
bisos/gcipher/Proxy.py
bisos/gcipher/__init__.py
bisos/gcipher/cipher/Caesar.py
bisos/gcipher/cipher/CharacterCipher.py
bisos/gcipher/cipher/Gie.py
bisos/gcipher/cipher/KeyedCipher.py
bisos/gcipher/cipher/Rot.py
bisos/gcipher/cipher/Tools.py
bisos/gcipher/cipher/Vigenere.py
bisos/gcipher/cipher/__init__.py
bisos/gcipher/ciphergui/Caesar.py
bisos/gcipher/ciphergui/CipherGUIList.py
bisos/gcipher/ciphergui/Gie.py
bisos/gcipher/ciphergui/KeyDialog.py
bisos/gcipher/ciphergui/Rot.py
bisos/gcipher/ciphergui/Vigenere.py
bisos/gcipher/ciphergui/__init__.py